onebudd/__init__.py
onebudd/client.py
onebudd-1.0.0.dist-info/METADATA
onebudd-1.0.0.dist-info/WHEEL
onebudd-1.0.0.dist-info/RECORD
