Metadata-Version: 2.4
Name: onebudd
Version: 1.0.0
Summary: OneBudd STS SDK - Real-time voice AI conversations
Author: OneBudd
License: MIT
Keywords: ai,onebudd,real-time,speech-to-text,text-to-speech,voice,websocket
Requires-Python: >=3.9
Requires-Dist: websockets>=12.0
Provides-Extra: dev
Requires-Dist: pytest-asyncio>=0.21; extra == 'dev'
Requires-Dist: pytest>=7.0; extra == 'dev'
